logsentry_agent/__init__.py
logsentry_agent/cli.py
logsentry_agent/config.py
logsentry_agent/envelope.py
logsentry_agent/fingerprint.py
logsentry_agent/health.py
logsentry_agent/http.py
logsentry_agent/identity.py
logsentry_agent/normalize.py
logsentry_agent/redact.py
logsentry_agent/run.py
logsentry_agent/security.py
logsentry_agent/signals.py
logsentry_agent/signer.py
logsentry_agent/spool.py
logsentry_agent/state.py
logsentry_agent/collectors/__init__.py
logsentry_agent/collectors/apache.py
logsentry_agent/collectors/docker.py
logsentry_agent/collectors/nginx.py
logsentry_agent/collectors/ssh.py
logsentry_agent/collectors/windows_eventlog.py
logsentry_agent/normalizers/__init__.py
logsentry_agent/normalizers/windows_eventlog.py
logsentry_agent/utils/__init__.py
logsentry_agent/utils/multiline.py
logsentry_agent/utils/saferegex.py
logsentry_agent/utils/timeparse.py
logsentry_agent-1.0.10.dist-info/METADATA
logsentry_agent-1.0.10.dist-info/WHEEL
logsentry_agent-1.0.10.dist-info/entry_points.txt
logsentry_agent-1.0.10.dist-info/top_level.txt
logsentry_agent-1.0.10.dist-info/RECORD
