Metadata-Version: 2.4
Name: logsentry-agent
Version: 1.0.10
Summary: LogSentry agent SDK and collectors.
Author: LogSentry
License: MIT
Requires-Python: >=3.10
Requires-Dist: requests>=2.31
Requires-Dist: PyYAML>=6.0
Requires-Dist: cryptography>=42.0
Provides-Extra: windows
Requires-Dist: pywin32>=306; extra == "windows"
